gumui/__init__.py
gumui/__init__.pyi
gumui/py.typed
gumui/runtime.py
gumui/FlatRedBall/Glue/StateInterpolation/__init__.pyi
gumui/Gum/__init__.pyi
gumui/Gum/Content/AnimationChain/__init__.pyi
gumui/Gum/Converters/__init__.pyi
gumui/Gum/DataTypes/__init__.pyi
gumui/Gum/DataTypes/Behaviors/__init__.pyi
gumui/Gum/DataTypes/Variables/__init__.pyi
gumui/Gum/Managers/__init__.pyi
gumui/Gum/Mvvm/__init__.pyi
gumui/Gum/RenderingLibrary/__init__.pyi
gumui/Gum/StateAnimation/Runtime/__init__.pyi
gumui/Gum/StateAnimation/SaveClasses/__init__.pyi
gumui/Gum/Wireframe/__init__.pyi
gumui/GumDataTypes/Variables/__init__.pyi
gumui/GumRuntime/__init__.pyi
gumui/GumToPython/__init__.pyi
gumui/MonoGameGum/Localization/__init__.pyi
gumui/RenderingLibrary/__init__.pyi
gumui/RenderingLibrary/Content/__init__.pyi
gumui/RenderingLibrary/Graphics/__init__.pyi
gumui/RenderingLibrary/Graphics/Fonts/__init__.pyi
gumui/RenderingLibrary/Math/__init__.pyi
gumui/ToolsUtilities/__init__.pyi
gumui/ToolsUtilitiesStandard/Helpers/__init__.pyi
gumui/ToolsUtilitiesStandard/Network/__init__.pyi
gumui/_clr/net6.0/FlatRedBall.InterpolationCore.dll
gumui/_clr/net6.0/GumCommon.deps.json
gumui/_clr/net6.0/GumCommon.dll
gumui/_clr/net6.0/GumCommon.pdb
gumui/_clr/net6.0/GumCommon.xml
gumui/_clr/net6.0/GumToPythonHelpers.deps.json
gumui/_clr/net6.0/GumToPythonHelpers.dll
gumui/_clr/net6.0/GumToPythonHelpers.pdb
gumui-0.1.3.dist-info/licenses/LICENSE
gumui-0.1.3.dist-info/METADATA
gumui-0.1.3.dist-info/WHEEL
gumui-0.1.3.dist-info/top_level.txt
gumui-0.1.3.dist-info/RECORD
