Metadata-Version: 2.4
Name: gumui
Version: 0.1.3
Summary: Python bindings for Gum UI (.NET runtime via PythonNET)
Author-email: Jeremy Swartwood <jeremy.swartwood@gmail.com>, Victor Chelaru <VicChelaru@gmail.com>
License-Expression: MIT
Requires-Python: >=3.8
License-File: LICENSE
Requires-Dist: pythonnet>=3.0.1
Dynamic: license-file
